excelextract/__init__.py
excelextract/cli.py
excelextract/extract.py
excelextract/formulas.py
excelextract/io.py
excelextract/logger.py
excelextract/lookup.py
excelextract/simpleTable.py
excelextract/tokens.py
excelextract/type.py
excelextract/utils.py
excelextract-1.0.0.dist-info/licenses/LICENSE
excelextract-1.0.0.dist-info/METADATA
excelextract-1.0.0.dist-info/WHEEL
excelextract-1.0.0.dist-info/entry_points.txt
excelextract-1.0.0.dist-info/top_level.txt
excelextract-1.0.0.dist-info/RECORD
