Metadata-Version: 2.4
Name: excelextract
Version: 1.0.0
Summary: A simple and flexible Excel-to-CSV extraction tool using JSON configuration.
Author: Philippe Debie
License-Expression: MIT
Project-URL: Homepage, https://github.com/philippe554/excelextract
Project-URL: Source, https://github.com/philippe554/excelextract
Project-URL: Tracker, https://github.com/philippe554/excelextract/issues
Classifier: Development Status :: 5 - Production/Stable
Classifier: Intended Audience :: End Users/Desktop
Classifier: Programming Language :: Python :: 3
Classifier: Programming Language :: Python :: 3.9
Classifier: Programming Language :: Python :: 3.10
Classifier: Programming Language :: Python :: 3.11
Classifier: Programming Language :: Python :: 3.12
Classifier: Programming Language :: Python :: 3.13
Classifier: Operating System :: OS Independent
Classifier: Topic :: Utilities
Classifier: Environment :: Console
Requires-Python: >=3.9
License-File: LICENSE
Requires-Dist: openpyxl>=3.0.6
Requires-Dist: formulas>=1.2.7
Dynamic: license-file
